generate_ascii/RobotoMono-VariableFont_wght.ttf
generate_ascii/__init__.py
generate_ascii/beats_audio_2-wallpaper-1920x1080.jpg
generate_ascii/big_hero_6_baymax-wallpaper-1920x1080.jpg
generate_ascii/chibi_spiderman-wallpaper-1920x1080.jpg
generate_ascii/kung_fu_panda_2_the_kaboom_of_doom-wallpaper-1920x1080.jpg
generate_ascii/minions_2015_movie-wallpaper-1920x1080.jpg
generate_ascii/new_windows_11-wallpaper-1920x1080.jpg
generate_ascii/pink_aesthetic-wallpaper-1920x1080.jpg
generate_ascii/synthesize.py
generate_ascii/yin_yang_2-wallpaper-1920x1080.jpg
generate_ascii-0.0.1.dist-info/LICENSE
generate_ascii-0.0.1.dist-info/METADATA
generate_ascii-0.0.1.dist-info/WHEEL
generate_ascii-0.0.1.dist-info/top_level.txt
generate_ascii-0.0.1.dist-info/RECORD
