Metadata-Version: 2.1
Name: generate-ascii
Version: 0.0.1
Summary: Generating ascii art from image
Author: Shekhar Kausalye
Author-email: shekharkausalye@gmail.com
Classifier: Programming Language :: Python :: 3
Classifier: License :: OSI Approved :: MIT License
Classifier: Operating System :: OS Independent
Requires-Python: >=3.7
License-File: LICENSE
